asyncprogressor/__init__.py
asyncprogressor/asyncprogressor.py
asyncprogressor-0.2.2.dist-info/LICENSE
asyncprogressor-0.2.2.dist-info/METADATA
asyncprogressor-0.2.2.dist-info/WHEEL
asyncprogressor-0.2.2.dist-info/top_level.txt
asyncprogressor-0.2.2.dist-info/RECORD
