Metadata-Version: 2.1
Name: asyncprogressor
Version: 0.2.2
Summary: Package for showing progress on your function based on last run
Home-page: https://github.com/Spr00t/asyncprogressor
Author: Vlad Nadzuga
Author-email: nadzuga0vlad@gmail.com    
License: UNKNOWN
Platform: UNKNOWN
Classifier: Programming Language :: Python :: 3
Classifier: License :: OSI Approved :: MIT License
Classifier: Operating System :: OS Independent
Requires-Python: >=3.6
Requires-Dist: tqdm
Requires-Dist: diskcache
